bin2cell/__init__.py
bin2cell/bin2cell.py
bin2cell/.ipynb_checkpoints/__init__-checkpoint.py
bin2cell/.ipynb_checkpoints/bin2cell-checkpoint.py
bin2cell-0.3.4.dist-info/licenses/LICENSE
bin2cell-0.3.4.dist-info/WHEEL
bin2cell-0.3.4.dist-info/METADATA
bin2cell-0.3.4.dist-info/RECORD
