Metadata-Version: 2.4
Name: bin2cell
Version: 0.3.4
Summary: Join subcellular Visium HD bins into cells
Author-email: "Krzysztof Polanski, Nadav Yayon" <kp9@sanger.ac.uk>
Requires-Python: >=3.7
Classifier: License :: OSI Approved :: MIT License
License-File: LICENSE
Requires-Dist: scanpy
Requires-Dist: opencv-python
Requires-Dist: scikit-image
Requires-Dist: fastparquet
Requires-Dist: numpy < 2 ; extra == "stardist"
Requires-Dist: stardist ; extra == "stardist"
Project-URL: Documentation, https://bin2cell.readthedocs.io/en/latest/
Project-URL: Home, https://github.com/Teichlab/bin2cell
Provides-Extra: stardist
